Dawnet-0.0.2.dist-info/METADATA
Dawnet-0.0.2.dist-info/RECORD
Dawnet-0.0.2.dist-info/WHEEL
Dawnet-0.0.2.dist-info/top_level.txt
dawnet/__init__.py
dawnet/data/__init__.py
dawnet/data/image.py
dawnet/data/text.py
dawnet/models/__init__.py
dawnet/models/base.py
dawnet/models/convs.py
dawnet/models/functions.py
dawnet/models/perceive.py
dawnet/training/__init__.py
dawnet/training/hyper.py
dawnet/training/review.py
dawnet/training/train.py
