Metadata-Version: 2.1
Name: Dawnet
Version: 0.0.2
Summary: A deep learning package to inquire intelligence
Home-page: https://github.com/johntd54/dawnet
Author: _john
Author-email: trungduc1992@gmail.com
License: GNU General Public License (GPL)
Keywords: dawnet deep learning inquire artificial intelligence
Platform: UNKNOWN
Classifier: Programming Language :: Python :: 3
Classifier: License :: OSI Approved :: GNU General Public License (GPL)
Classifier: Operating System :: OS Independent
Requires-Python: >=3.5
Requires-Dist: numpy (>=1.14.0)
Requires-Dist: Pillow (>=5.3.0)
Requires-Dist: matplotlib (>=2.1.2)
